Metadata-Version: 1.0
Name: gaussian-binomial-dists-fp
Version: 0.1
Summary: Gaussian & Binomial distributions
Home-page: UNKNOWN
Author: Florian Perras
Author-email: Flo92-Perras@web.de
License: UNKNOWN
Platform: UNKNOWN
